azure/mgmt/databricks/__init__.py
azure/mgmt/databricks/_azure_databricks_management_client.py
azure/mgmt/databricks/_configuration.py
azure/mgmt/databricks/_patch.py
azure/mgmt/databricks/_serialization.py
azure/mgmt/databricks/_vendor.py
azure/mgmt/databricks/_version.py
azure/mgmt/databricks/py.typed
azure/mgmt/databricks/aio/__init__.py
azure/mgmt/databricks/aio/_azure_databricks_management_client.py
azure/mgmt/databricks/aio/_configuration.py
azure/mgmt/databricks/aio/_patch.py
azure/mgmt/databricks/aio/operations/__init__.py
azure/mgmt/databricks/aio/operations/_access_connectors_operations.py
azure/mgmt/databricks/aio/operations/_operations.py
azure/mgmt/databricks/aio/operations/_outbound_network_dependencies_endpoints_operations.py
azure/mgmt/databricks/aio/operations/_patch.py
azure/mgmt/databricks/aio/operations/_private_endpoint_connections_operations.py
azure/mgmt/databricks/aio/operations/_private_link_resources_operations.py
azure/mgmt/databricks/aio/operations/_vnet_peering_operations.py
azure/mgmt/databricks/aio/operations/_workspaces_operations.py
azure/mgmt/databricks/models/__init__.py
azure/mgmt/databricks/models/_azure_databricks_management_client_enums.py
azure/mgmt/databricks/models/_models_py3.py
azure/mgmt/databricks/models/_patch.py
azure/mgmt/databricks/operations/__init__.py
azure/mgmt/databricks/operations/_access_connectors_operations.py
azure/mgmt/databricks/operations/_operations.py
azure/mgmt/databricks/operations/_outbound_network_dependencies_endpoints_operations.py
azure/mgmt/databricks/operations/_patch.py
azure/mgmt/databricks/operations/_private_endpoint_connections_operations.py
azure/mgmt/databricks/operations/_private_link_resources_operations.py
azure/mgmt/databricks/operations/_vnet_peering_operations.py
azure/mgmt/databricks/operations/_workspaces_operations.py
azure_mgmt_databricks-2.0.0.dist-info/LICENSE
azure_mgmt_databricks-2.0.0.dist-info/METADATA
azure_mgmt_databricks-2.0.0.dist-info/WHEEL
azure_mgmt_databricks-2.0.0.dist-info/top_level.txt
azure_mgmt_databricks-2.0.0.dist-info/RECORD
